[
  {
    "id": "nailmag",
    "looks_like": "stanag30",
    "type": "MAGAZINE",
    "name": { "str": "nail rifle magazine (SzQmod)" },
    "description": "An improvised magazine for use with a nail rifle.  Little more than a tin can, spring and some duct tape it is awkward to reload and not especially reliable.",
    "weight": "60 g",
    "volume": "250 ml",
    "price": "19 USD",
    "material": [ "steel" ],
    "symbol": "#",
    "color": "light_gray",
    "ammo_type": [ "nail" ],
    "capacity": 50,
    "reliability": 6,
    "reload_time": 300,
    "flags": [ "MAG_COMPACT" ]
  },
  {
    "id": "tihar24mag",
    "looks_like": "stanag30",
    "type": "MAGAZINE",
    "name": { "str": "Tihar magazine" },
    "description": "An improvised magazine for use with a Tihar.  Little more than a pipe, spring and some duct tape it is awkward to reload and not especially reliable.",
    "weight": "180 g",
    "volume": "250 ml",
    "price": "19 USD",
    "material": [ "steel" ],
    "symbol": "#",
    "color": "light_gray",
    "ammo_type": [ "pebble" ],
    "capacity": 24,
    "reliability": 6,
    "reload_time": 800,
    "flags": [ "MAG_COMPACT" ]
  },
  {
    "id": "bb_hopper",
    "type": "MAGAZINE",
    "name": "BB hopper (SzQmod)",
    "description": "An improvised magazine for a vehicle mounted weapon.  A simple metal box with some plastic guide rails, it acts as a gravity fed hopper to drop a small round shot into the weapon's chamber below.  It is not very reliable, but quick to reload.",
    "weight": "1840 g",
    "volume": "3 L",
    "price": "166 USD",
    "material": "steel",
    "symbol": "#",
    "color": "light_gray",
    "ammo_type": "BB",
    "capacity": 250,
    "reliability": 6,
    "reload_time": 15
  },
  {
    "id": "bolt_hopper",
    "looks_like": "bb_hopper",
    "type": "MAGAZINE",
    "name": "bolt hopper (SzQmod)",
    "description": "An improvised magazine for a vehicle mounted crossbow.  A simple metal box with some plastic guide rails, it acts as a gravity fed hopper to drop a crossbow bolt into the weapon below.  It is awkward to reload and not especially reliable.",
    "weight": "1840 g",
    "volume": "3 L",
    "price": "166 USD",
    "material": "steel",
    "symbol": "#",
    "color": "light_gray",
    "ammo_type": "bolt",
    "capacity": 60,
    "reliability": 6,
    "reload_time": 150
  },
  {
    "id": "cannister_rack",
    "looks_like": "bb_hopper",
    "type": "MAGAZINE",
    "name": "canister rack (SzQmod)",
    "description": "An improvised magazine for a vehicle mounted weapon.  A simple metal box with some plastic guide rails, it acts as a gravity fed hopper to drop a heavy canister into the weapon below.  It is awkward to reload and not especially reliable.",
    "weight": "1840 g",
    "volume": "3 L",
    "price": "166 USD",
    "material": "steel",
    "symbol": "#",
    "color": "light_gray",
    "ammo_type": "h_projectile",
    "capacity": 8,
    "reliability": 6,
    "reload_time": 150
  },
  {
    "id": "pebble_hopper",
    "looks_like": "bb_hopper",
    "type": "MAGAZINE",
    "name": "pebble hopper (SzQmod)",
    "description": "An improvised magazine for a vehicle mounted weapon.  A simple metal box with some plastic guide rails, it acts as a gravity fed hopper to drop a small round shot into the weapon's chamber below.  It is not very reliable, but quick to reload.",
    "weight": "1840 g",
    "volume": "3 L",
    "price": "166 USD",
    "material": "steel",
    "symbol": "#",
    "color": "light_gray",
    "ammo_type": "pebble",
    "capacity": 250,
    "reliability": 6,
    "reload_time": 15
  }
]
