[
  {
    "abstract": "turret_manual_blaze",
    "copy-from": "turret",
    "type": "vehicle_part",
    "broken_symbol": "#",
    "description": "This heavy weapon is mounted on a turret, and can be fired from your vehicle controls."
  },
  {
    "id": "mounted_coilgun",
    "looks_like": "coilgun",
    "copy-from": "turret",
    "type": "vehicle_part",
    "name": { "str": "mounted coilgun (SzQmod)" },
    "item": "coilgun",
    "color": "magenta",
    "broken_color": "magenta",
    "breaks_into": [ { "item": "scrap", "count": 13 }, { "item": "steel_chunk", "count": 4 }, { "item": "steel_lump", "count": 1 } ],
    "requirements": {
      "install": { "skills": [ [ "mechanics", 5 ], [ "electronics", 5 ] ] },
      "removal": { "skills": [ [ "mechanics", 3 ] ] }
    }
  },
  {
    "id": "shardgun",
    "//1": "BB",
    "looks_like": "shardgun",
    "copy-from": "turret_manual_blaze",
    "type": "vehicle_part",
    "name": "splintergun (SzQmod)",
    "item": "shardgun",
    "color": "blue",
    "broken_color": "blue",
    "breaks_into": [ { "item": "shardgun", "count": [ 0, 1 ] } ],
    "requirements": {
      "install": { "skills": [ [ "mechanics", 6 ] ], "time": "60 m", "using": [ [ "vehicle_bolt", 1 ] ] },
      "removal": { "skills": [ [ "mechanics", 4 ] ], "time": "45 m", "using": [ [ "vehicle_bolt", 1 ] ] },
      "repair": { "skills": [ [ "mechanics", 5 ] ], "time": "25 m", "using": [ [ "welding_standard", 5 ] ] }
    }
  },
  {
    "id": "vortexaccelerator",
    "looks_like": "vortexaccelerator",
    "copy-from": "turret_manual_blaze",
    "type": "vehicle_part",
    "name": "vortex accelerator (SzQmod)",
    "item": "vortexaccelerator",
    "color": "pink",
    "broken_color": "pink",
    "size": 1000,
    "folded_volume": 10,
    "breaks_into": [ { "item": "vortexaccelerator", "count": [ 0, 1 ] } ],
    "requirements": {
      "install": { "skills": [ [ "mechanics", 4 ] ], "time": "25 m", "using": [ [ "vehicle_bolt", 1 ] ] },
      "removal": { "skills": [ [ "mechanics", 3 ] ], "time": "20 m", "using": [ [ "vehicle_bolt", 1 ] ] },
      "repair": { "skills": [ [ "mechanics", 3 ] ], "time": "15 m", "using": [ [ "welding_standard", 5 ] ] }
    }
  },
  {
    "id": "nailer",
    "//1": "//nail",
    "looks_like": "nailer",
    "copy-from": "turret_manual_blaze",
    "type": "vehicle_part",
    "name": "perforator (SzQmod)",
    "item": "nailer",
    "color": "dark_gray",
    "broken_color": "dark_gray",
    "breaks_into": [ { "item": "nailer", "count": [ 0, 1 ] } ],
    "requirements": {
      "install": { "skills": [ [ "mechanics", 5 ] ], "time": "60 m", "using": [ [ "vehicle_bolt", 1 ] ] },
      "removal": { "skills": [ [ "mechanics", 3 ] ], "time": "45 m", "using": [ [ "vehicle_bolt", 1 ] ] },
      "repair": { "skills": [ [ "mechanics", 4 ] ], "time": "25 m", "using": [ [ "welding_standard", 5 ] ] }
    }
  },
  {
    "id": "needler",
    "looks_like": "needler",
    "copy-from": "turret_manual_blaze",
    "type": "vehicle_part",
    "name": "needler (SzQmod)",
    "item": "needler",
    "color": "blue",
    "broken_color": "blue",
    "breaks_into": [ { "item": "needler", "count": [ 0, 1 ] } ],
    "requirements": {
      "install": { "skills": [ [ "mechanics", 5 ] ], "time": "60 m", "using": [ [ "vehicle_bolt", 1 ] ] },
      "removal": { "skills": [ [ "mechanics", 3 ] ], "time": "45 m", "using": [ [ "vehicle_bolt", 1 ] ] },
      "repair": { "skills": [ [ "mechanics", 4 ] ], "time": "25 m", "using": [ [ "welding_standard", 5 ] ] }
    }
  },
  {
    "id": "bolter",
    "//1": "//bolt",
    "looks_like": "bolter",
    "copy-from": "turret_manual_blaze",
    "type": "vehicle_part",
    "name": "storm bolter (SzQmod)",
    "item": "bolter",
    "color": "light_gray",
    "broken_color": "light_gray",
    "breaks_into": [ { "item": "bolter", "count": [ 0, 1 ] } ],
    "requirements": {
      "install": { "skills": [ [ "mechanics", 4 ] ], "time": "60 m", "using": [ [ "vehicle_bolt", 1 ] ] },
      "removal": { "skills": [ [ "mechanics", 2 ] ], "time": "45 m", "using": [ [ "vehicle_bolt", 1 ] ] },
      "repair": { "skills": [ [ "mechanics", 3 ] ], "time": "25 m", "using": [ [ "welding_standard", 5 ] ] }
    }
  },
  {
    "id": "vortexbolter",
    "looks_like": "vortexbolter",
    "copy-from": "turret_manual_blaze",
    "type": "vehicle_part",
    "name": "vortex bolter turret (SzQmod)",
    "item": "vortexbolter",
    "color": "pink",
    "broken_color": "pink",
    "size": 10,
    "folded_volume": 10,
    "breaks_into": [ { "item": "vortexbolter", "count": [ 0, 1 ] } ],
    "requirements": {
      "install": { "skills": [ [ "mechanics", 4 ] ], "time": "60 m", "using": [ [ "vehicle_bolt", 1 ] ] },
      "removal": { "skills": [ [ "mechanics", 2 ] ], "time": "45 m", "using": [ [ "vehicle_bolt", 1 ] ] },
      "repair": { "skills": [ [ "mechanics", 3 ] ], "time": "25 m", "using": [ [ "welding_standard", 5 ] ] }
    }
  },
  {
    "id": "scorpion",
    "//1": "//hbolt",
    "looks_like": "scorpion",
    "copy-from": "turret_manual_blaze",
    "type": "vehicle_part",
    "name": "scorpion ballista (SzQmod)",
    "item": "scorpion",
    "color": "brown",
    "broken_color": "brown",
    "breaks_into": [ { "item": "scorpion", "count": [ 0, 1 ] } ],
    "requirements": {
      "install": { "skills": [ [ "mechanics", 4 ] ], "time": "60 m", "using": [ [ "vehicle_bolt", 1 ] ] },
      "removal": { "skills": [ [ "mechanics", 2 ] ], "time": "45 m", "using": [ [ "vehicle_bolt", 1 ] ] },
      "repair": { "skills": [ [ "mechanics", 3 ] ], "time": "25 m", "using": [ [ "welding_standard", 5 ] ] }
    }
  },
  {
    "id": "rslauncher",
    "//1": "//harpoon",
    "looks_like": "rslauncher",
    "copy-from": "turret_manual_blaze",
    "type": "vehicle_part",
    "name": "rotary speargun (SzQmod)",
    "item": "rslauncher",
    "color": "light_gray",
    "broken_color": "light_gray",
    "breaks_into": [ { "item": "rslauncher", "count": [ 0, 1 ] } ],
    "requirements": {
      "install": { "skills": [ [ "mechanics", 5 ] ], "time": "60 m", "using": [ [ "vehicle_bolt", 1 ] ] },
      "removal": { "skills": [ [ "mechanics", 3 ] ], "time": "45 m", "using": [ [ "vehicle_bolt", 1 ] ] },
      "repair": { "skills": [ [ "mechanics", 4 ] ], "time": "25 m", "using": [ [ "welding_standard", 5 ] ] }
    }
  },
  {
    "id": "slauncher",
    "looks_like": "slauncher",
    "copy-from": "turret_manual_blaze",
    "type": "vehicle_part",
    "name": "speargun (SzQmod)",
    "item": "slauncher",
    "color": "light_gray",
    "broken_color": "light_gray",
    "breaks_into": [ { "item": "slauncher", "count": [ 0, 1 ] } ],
    "requirements": {
      "install": { "skills": [ [ "mechanics", 3 ] ], "time": "60 m", "using": [ [ "vehicle_bolt", 1 ] ] },
      "removal": { "skills": [ [ "mechanics", 1 ] ], "time": "45 m", "using": [ [ "vehicle_bolt", 1 ] ] },
      "repair": { "skills": [ [ "mechanics", 2 ] ], "time": "25 m", "using": [ [ "welding_standard", 5 ] ] }
    }
  },
  {
    "id": "tiharturret",
    "//1": "//pebble",
    "looks_like": "tiharturret",
    "copy-from": "turret_manual_blaze",
    "type": "vehicle_part",
    "name": "avalanche rifle (SzQmod)",
    "item": "tiharturret",
    "color": "light_gray",
    "broken_color": "light_gray",
    "breaks_into": [ { "item": "tiharturret", "count": [ 0, 1 ] } ],
    "requirements": {
      "install": { "skills": [ [ "mechanics", 4 ] ], "time": "60 m", "using": [ [ "vehicle_bolt", 1 ] ] },
      "removal": { "skills": [ [ "mechanics", 2 ] ], "time": "45 m", "using": [ [ "vehicle_bolt", 1 ] ] },
      "repair": { "skills": [ [ "mechanics", 3 ] ], "time": "25 m", "using": [ [ "welding_standard", 5 ] ] }
    }
  },
  {
    "id": "vortexrifle",
    "looks_like": "vortexrifle",
    "copy-from": "turret_manual_blaze",
    "type": "vehicle_part",
    "name": "vortex rifle (SzQmod)",
    "item": "vortexrifle",
    "color": "pink",
    "broken_color": "pink",
    "difficulty": 4,
    "size": 40,
    "folded_volume": 10,
    "breaks_into": [ { "item": "vortexrifle", "count": [ 0, 1 ] } ],
    "requirements": {
      "install": { "skills": [ [ "mechanics", 4 ] ], "time": "60 m", "using": [ [ "vehicle_bolt", 1 ] ] },
      "removal": { "skills": [ [ "mechanics", 2 ] ], "time": "45 m", "using": [ [ "vehicle_bolt", 1 ] ] },
      "repair": { "skills": [ [ "mechanics", 3 ] ], "time": "25 m", "using": [ [ "welding_standard", 5 ] ] }
    }
  },
  {
    "id": "mounted_rebar_rifle",
    "//1": "//metal_rail",
    "looks_like": "mounted_rebar_rifle",
    "copy-from": "turret",
    "type": "vehicle_part",
    "name": { "str": "mounted ferromagnetic rail rifle (SzQmod)" },
    "item": "rebar_rifle",
    "color": "magenta",
    "broken_color": "magenta",
    "breaks_into": [ { "item": "scrap", "count": 9 }, { "item": "steel_chunk", "count": 5 }, { "item": "steel_lump", "count": 2 } ],
    "requirements": {
      "install": { "skills": [ [ "mechanics", 5 ], [ "electronics", 5 ] ] },
      "removal": { "skills": [ [ "mechanics", 3 ] ] }
    }
  },
  {
    "id": "railturret",
    "looks_like": "railturret",
    "copy-from": "turret_manual_blaze",
    "type": "vehicle_part",
    "name": "hypervelocity driver (SzQmod)",
    "item": "railturret",
    "color": "magenta",
    "broken_color": "magenta",
    "breaks_into": [ { "item": "railturret", "count": [ 0, 1 ] } ],
    "requirements": {
      "install": { "skills": [ [ "mechanics", 5 ] ], "time": "60 m", "using": [ [ "vehicle_bolt", 1 ] ] },
      "removal": { "skills": [ [ "mechanics", 3 ] ], "time": "45 m", "using": [ [ "vehicle_bolt", 1 ] ] },
      "repair": { "skills": [ [ "mechanics", 4 ] ], "time": "25 m", "using": [ [ "welding_standard", 5 ] ] }
    }
  },
  {
    "id": "mounted_heavy_rail_rifle",
    "looks_like": "mounted_heavy_rail_rifle",
    "copy-from": "turret",
    "type": "vehicle_part",
    "name": { "str": "mounted heavy rail rifle (SzQmod)" },
    "item": "heavy_rail_rifle",
    "color": "magenta",
    "broken_color": "magenta",
    "breaks_into": [ { "item": "scrap", "count": 30 }, { "item": "steel_chunk", "count": 10 }, { "item": "steel_lump", "count": 6 } ],
    "requirements": {
      "install": { "skills": [ [ "mechanics", 5 ], [ "electronics", 5 ] ] },
      "removal": { "skills": [ [ "mechanics", 3 ] ] }
    }
  },
  {
    "id": "vortexcannon",
    "looks_like": "vortexcannon",
    "copy-from": "turret_manual_blaze",
    "type": "vehicle_part",
    "name": "vortex cannon (SzQmod)",
    "item": "vortexcannon",
    "color": "pink",
    "broken_color": "pink",
    "size": 10,
    "folded_volume": 20,
    "breaks_into": [ { "item": "vortexcannon", "count": [ 0, 1 ] } ],
    "requirements": {
      "install": { "skills": [ [ "mechanics", 4 ] ], "time": "25 m", "using": [ [ "vehicle_bolt", 1 ] ] },
      "removal": { "skills": [ [ "mechanics", 3 ] ], "time": "20 m", "using": [ [ "vehicle_bolt", 1 ] ] },
      "repair": { "skills": [ [ "mechanics", 3 ] ], "time": "15 m", "using": [ [ "welding_standard", 5 ] ] }
    }
  },
  {
    "id": "cutter",
    "//1": "//ripdisk",
    "looks_like": "cutter",
    "copy-from": "turret_manual_blaze",
    "type": "vehicle_part",
    "name": "lacerator (SzQmod)",
    "item": "cutter",
    "broken_symbol": "x",
    "color": "dark_gray",
    "broken_color": "dark_gray",
    "power": -1750,
    "breaks_into": [ { "item": "cutter", "count": [ 0, 1 ] } ],
    "requirements": {
      "install": { "skills": [ [ "mechanics", 5 ] ], "time": "60 m", "using": [ [ "vehicle_bolt", 1 ] ] },
      "removal": { "skills": [ [ "mechanics", 3 ] ], "time": "45 m", "using": [ [ "vehicle_bolt", 1 ] ] },
      "repair": { "skills": [ [ "mechanics", 4 ] ], "time": "25 m", "using": [ [ "welding_standard", 5 ] ] }
    },
    "extend": { "flags": [ "EXTRA_DRAG" ] }
  },
  {
    "id": "ripper",
    "looks_like": "ripper",
    "copy-from": "turret_manual_blaze",
    "type": "vehicle_part",
    "name": "ripper (SzQmod)",
    "item": "ripper",
    "broken_symbol": "x",
    "color": "dark_gray",
    "broken_color": "dark_gray",
    "power": -8750,
    "breaks_into": [ { "item": "ripper", "count": [ 0, 1 ] } ],
    "requirements": {
      "install": { "skills": [ [ "mechanics", 5 ] ], "time": "60 m", "using": [ [ "vehicle_bolt", 1 ] ] },
      "removal": { "skills": [ [ "mechanics", 3 ] ], "time": "45 m", "using": [ [ "vehicle_bolt", 1 ] ] },
      "repair": { "skills": [ [ "mechanics", 4 ] ], "time": "25 m", "using": [ [ "welding_standard", 5 ] ] }
    },
    "extend": { "flags": [ "EXTRA_DRAG" ] }
  },
  {
    "id": "lasgun",
    "//1": "//Lasers",
    "looks_like": "lasgun",
    "copy-from": "turret_manual_blaze",
    "type": "vehicle_part",
    "name": "laser cannon (SzQmod)",
    "item": "lasgun",
    "color": "blue",
    "broken_color": "blue",
    "breaks_into": [ { "item": "lasgun", "count": [ 0, 1 ] } ],
    "requirements": {
      "install": { "skills": [ [ "mechanics", 6 ] ], "time": "60 m", "using": [ [ "vehicle_bolt", 1 ] ] },
      "removal": { "skills": [ [ "mechanics", 4 ] ], "time": "45 m", "using": [ [ "vehicle_bolt", 1 ] ] },
      "repair": { "skills": [ [ "mechanics", 5 ] ], "time": "25 m", "using": [ [ "welding_standard", 5 ] ] }
    }
  },
  {
    "id": "lasgunp",
    "looks_like": "lasgunp",
    "copy-from": "turret_manual_blaze",
    "type": "vehicle_part",
    "name": "pulse laser (SzQmod)",
    "item": "lasgunp",
    "color": "blue",
    "broken_color": "blue",
    "breaks_into": [ { "item": "lasgun", "count": [ 0, 1 ] } ],
    "requirements": {
      "install": { "skills": [ [ "mechanics", 6 ] ], "time": "60 m", "using": [ [ "vehicle_bolt", 1 ] ] },
      "removal": { "skills": [ [ "mechanics", 4 ] ], "time": "45 m", "using": [ [ "vehicle_bolt", 1 ] ] },
      "repair": { "skills": [ [ "mechanics", 5 ] ], "time": "25 m", "using": [ [ "welding_standard", 5 ] ] }
    }
  },
  {
    "id": "lasgunx",
    "looks_like": "lasgunx",
    "copy-from": "turret_manual_blaze",
    "type": "vehicle_part",
    "name": "turbolaser (SzQmod)",
    "item": "lasgunx",
    "color": "magenta",
    "broken_color": "magenta",
    "breaks_into": [ { "item": "lasgunx", "count": [ 0, 1 ] } ],
    "requirements": {
      "install": { "skills": [ [ "mechanics", 6 ] ], "time": "60 m", "using": [ [ "vehicle_bolt", 1 ] ] },
      "removal": { "skills": [ [ "mechanics", 4 ] ], "time": "45 m", "using": [ [ "vehicle_bolt", 1 ] ] },
      "repair": { "skills": [ [ "mechanics", 5 ] ], "time": "25 m", "using": [ [ "welding_standard", 5 ] ] }
    }
  },
  {
    "id": "cangun",
    "//1": "//h_projectile",
    "looks_like": "cangun",
    "copy-from": "turret_manual_blaze",
    "type": "vehicle_part",
    "name": "slingshot cannon (SzQmod)",
    "item": "cangun",
    "color": "brown",
    "broken_color": "brown",
    "breaks_into": [ { "item": "cangun", "count": [ 0, 1 ] } ],
    "requirements": {
      "install": { "skills": [ [ "mechanics", 4 ] ], "time": "60 m", "using": [ [ "vehicle_bolt", 1 ] ] },
      "removal": { "skills": [ [ "mechanics", 2 ] ], "time": "45 m", "using": [ [ "vehicle_bolt", 1 ] ] },
      "repair": { "skills": [ [ "mechanics", 3 ] ], "time": "25 m", "using": [ [ "welding_standard", 5 ] ] }
    }
  },
  {
    "id": "gattler",
    "//1": "//other shit",
    "looks_like": "gattler",
    "copy-from": "turret_manual_blaze",
    "type": "vehicle_part",
    "name": "rotary cannon (SzQmod)",
    "item": "gattler",
    "color": "dark_gray",
    "broken_color": "dark_gray",
    "breaks_into": [ { "item": "gattler", "count": [ 0, 1 ] } ],
    "requirements": {
      "install": { "skills": [ [ "mechanics", 5 ] ], "time": "60 m", "using": [ [ "vehicle_bolt", 1 ] ] },
      "removal": { "skills": [ [ "mechanics", 3 ] ], "time": "45 m", "using": [ [ "vehicle_bolt", 1 ] ] },
      "repair": { "skills": [ [ "mechanics", 4 ] ], "time": "25 m", "using": [ [ "welding_standard", 5 ] ] }
    }
  },
  {
    "id": "flamethrower3",
    "looks_like": "flamethrower",
    "copy-from": "turret_manual_blaze",
    "type": "vehicle_part",
    "name": "RM451 flamethrower (SzQmod)",
    "item": "rm451_flamethrower",
    "color": "red",
    "broken_color": "red",
    "breaks_into": [ { "item": "rm451_flamethrower", "count": [ 0, 1 ] } ],
    "requirements": {
      "install": { "skills": [ [ "mechanics", 4 ] ], "time": "60 m", "using": [ [ "vehicle_bolt", 1 ] ] },
      "removal": { "skills": [ [ "mechanics", 2 ] ], "time": "45 m", "using": [ [ "vehicle_bolt", 1 ] ] },
      "repair": { "skills": [ [ "mechanics", 3 ] ], "time": "25 m", "using": [ [ "welding_standard", 5 ] ] }
    },
    "extend": { "flags": [ "USE_TANKS" ] }
  },
  {
    "id": "teslagun",
    "looks_like": "teslagun",
    "copy-from": "turret_manual_blaze",
    "type": "vehicle_part",
    "name": "tesla cannon (SzQmod)",
    "item": "teslagun",
    "color": "blue",
    "broken_color": "blue",
    "breaks_into": [ { "item": "teslagun", "count": [ 0, 1 ] } ],
    "requirements": {
      "install": { "skills": [ [ "mechanics", 3 ] ], "time": "60 m", "using": [ [ "vehicle_bolt", 1 ] ] },
      "removal": { "skills": [ [ "mechanics", 1 ] ], "time": "45 m", "using": [ [ "vehicle_bolt", 1 ] ] },
      "repair": { "skills": [ [ "mechanics", 2 ] ], "time": "25 m", "using": [ [ "welding_standard", 5 ] ] }
    }
  },
  {
    "id": "mounted_mininuke_launcher",
    "copy-from": "turret",
    "type": "vehicle_part",
    "name": { "str": "mounted mininuke launcher" },
    "item": "mininuke_launcher",
    "color": "green",
    "broken_color": "green",
    "breaks_into": [ { "item": "scrap", "count": 27 }, { "item": "steel_chunk", "count": 10 }, { "item": "steel_lump", "count": 6 } ],
    "requirements": { "install": { "skills": [ [ "mechanics", 5 ], [ "launcher", 3 ] ] }, "removal": { "skills": [ [ "mechanics", 3 ] ] } }
  }
]
